imgpd/__init__.py
imgpd/__main__.py
imgpd/ipd.py
imgpd/modules/__init__.py
imgpd/modules/fileTasks/__init__.py
imgpd/modules/getPalette/__init__.py
imgpd/modules/gui/__init__.py
imgpd/modules/inputDialogs/__init__.py
imgpd/modules/main/__init__.py
imgpd-0.3.0.dist-info/LICENSE
imgpd-0.3.0.dist-info/METADATA
imgpd-0.3.0.dist-info/WHEEL
imgpd-0.3.0.dist-info/top_level.txt
imgpd-0.3.0.dist-info/RECORD
