Metadata-Version: 2.1
Name: imgpd
Version: 0.3.0
Summary: Fast and accurate image RGB palette detector by Eugene Gourieff
Home-page: https://github.com/Gourieff/img-palette-detector
Author: Eugene Gourieff
Author-email: Eugene Gourieff <gourieff@gmail.com>
License: GPL-3.0
Project-URL: Homepage, https://github.com/Gourieff/img-palette-detector
Project-URL: Bug Tracker, https://github.com/Gourieff/img-palette-detector/issues
Classifier: Programming Language :: Python :: 3
Classifier: License :: OSI Approved :: GNU General Public License v3 (GPLv3)
Classifier: Operating System :: OS Independent
Requires-Python: >=3.7
License-File: LICENSE
Requires-Dist: opencv-python
Requires-Dist: colorthief
Requires-Dist: argparse
Requires-Dist: pysimplegui
